{
  "format": 1,
  "engine": "smsh-sequence-sidecar",
  "name": "sound_089",
  "tracks": {
    "track_1": {
      "events": 34,
      "hash": "dc9d06989b2184c3",
      "deviations": [
        [6,1,["note",5,68]],
        [7,1,["note",5,71]],
        [10,1,["note",5,66]],
        [11,1,["note",5,69]],
        [14,1,["note",15,68]],
        [15,1,["note",15,71]],
        [18,1,["note",5,71]],
        [19,1,["note",5,74]],
        [22,1,["note",5,71]],
        [23,1,["note",5,74]],
        [26,1,["note",5,71]],
        [27,1,["note",5,74]],
        [30,1,["note",23,68]],
        [31,1,["note",23,71]]
      ]
    },
    "track_4": {
      "events": 29,
      "hash": "0d7fc3ec2e182b1f",
      "deviations": [
        [26,1,["note",23,49]]
      ]
    }
  }
}
