{"format":1,"codec":"golden-sun-static-sprite-bank","width":64,"height":64,"atlas_columns":8,"alignment_zeros":0,"frames":[{"format":1,"codec":"golden-sun-static-sprite-mode3","pixels":4096,"stream_bytes":316,"encoded_bytes":318,"wrapper":{"split":0}},{"format":1,"codec":"golden-sun-static-sprite-mode3","pixels":4096,"stream_bytes":248,"encoded_bytes":166,"wrapper":{"split":121,"operations":[["c",318,40],["l",2],["c",275,3],["l",15],["c",136,3],["l",2],["c",141,5],["l",7],["c",278,4],["l",10],["c",224,3],["l",5],["c",278,3],["l",19],["c",253,3],["l",10],["c",184,3],["l",24],["c",272,4],["l",24],["c",318,16],["c",318,42],["l",1]]}},{"format":1,"codec":"golden-sun-static-sprite-mode3","pixels":4096,"stream_bytes":316,"encoded_bytes":222,"wrapper":{"split":137,"operations":[["c",484,42],["l",2],["c",388,3],["l",4],["c",94,5],["l",8],["c",417,5],["l",1],["c",411,5],["l",8],["c",398,3],["l",3],["c",391,4],["l",1],["c",386,5],["l",1],["c",380,4],["c",419,3],["l",11],["c",117,4],["c",312,3],["l",5],["c",350,4],["l",6],["c",159,3],["l",2],["c",86,3],["l",2],["c",331,4],["l",1],["c",442,3],["l",1],["c",164,3],["l",1],["c",319,6],["l",1],["c",312,3],["l",3],["c",306,4],["l",1],["c",301,3],["l",1],["c",152,3],["l",25],["c",266,3],["l",5],["c",263,5],["l",4],["c",254,3],["l",5],["c",253,3],["l",7],["c",339,3],["l",18],["c",215,3],["l",8],["c",204,36]]}},{"format":1,"codec":"golden-sun-static-sprite-mode3","pixels":4096,"stream_bytes":249,"encoded_bytes":144,"wrapper":{"split":90,"operations":[["c",706,40],["l",2],["c",663,3],["l",1],["c",385,13],["c",299,3],["l",3],["c",640,3],["l",10],["c",666,3],["l",7],["c",666,3],["c",612,3],["l",14],["c",340,4],["l",1],["c",335,3],["l",8],["c",328,3],["l",1],["c",324,5],["l",1],["c",572,3],["l",18],["c",300,6],["c",660,4],["l",3],["c",291,4],["l",18],["c",706,16],["c",706,42],["l",1]]}},{"format":1,"codec":"golden-sun-static-sprite-mode3","pixels":4096,"stream_bytes":311,"encoded_bytes":187,"wrapper":{"split":91,"operations":[["c",850,46],["c",256,3],["l",3],["c",460,5],["c",360,5],["l",1],["c",785,5],["l",4],["c",776,4],["l",5],["c",792,3],["c",764,3],["l",8],["c",753,4],["l",3],["c",746,5],["l",1],["c",740,6],["l",5],["c",730,4],["l",1],["c",457,4],["l",4],["c",716,7],["l",2],["c",707,3],["l",1],["c",703,3],["l",10],["c",690,3],["l",1],["c",699,3],["c",458,3],["c",804,4],["c",78,3],["c",674,6],["l",1],["c",667,4],["c",518,3],["l",4],["c",655,3],["l",1],["c",294,4],["c",417,3],["c",641,8],["c",277,3],["c",669,3],["c",582,3],["l",5],["c",626,4],["l",17],["c",256,3],["l",5],["c",434,3],["l",1],["c",586,4],["l",5],["c",577,3],["c",235,3],["l",1],["c",570,36]]}},{"format":1,"codec":"golden-sun-static-sprite-mode3","pixels":4096,"stream_bytes":242,"encoded_bytes":125,"wrapper":{"split":58,"operations":[["c",1037,40],["l",2],["c",797,5],["l",1],["c",713,5],["l",1],["c",707,5],["l",4],["c",860,4],["l",4],["c",697,4],["c",303,3],["l",1],["c",693,6],["l",10],["c",304,3],["l",7],["c",851,3],["l",2],["c",666,3],["l",1],["c",662,3],["c",972,3],["c",659,3],["l",1],["c",655,3],["l",3],["c",993,3],["c",283,8],["l",1],["c",622,3],["l",5],["c",631,3],["l",1],["c",444,3],["l",1],["c",912,3],["l",6],["c",617,5],["l",1],["c",611,3],["l",3],["c",605,4],["c",1037,16],["c",1037,42],["l",1]]}},{"format":1,"codec":"golden-sun-static-sprite-mode3","pixels":4096,"stream_bytes":233,"encoded_bytes":187,"wrapper":{"split":120,"operations":[["l",6],["c",374,3],["l",1],["c",842,3],["l",5],["c",991,3],["l",3],["c",413,3],["l",8],["c",920,3],["l",4],["c",609,3],["l",4],["c",731,4],["l",2],["c",730,3],["l",12],["c",593,4],["l",2],["c",1078,3],["l",6],["c",1028,3],["l",9],["c",1118,3],["l",1],["c",1097,3],["l",1],["c",1003,3],["l",2],["c",1118,3],["l",5],["c",594,4],["l",3],["c",1078,3],["l",6],["c",1118,3],["l",1],["c",1078,3],["l",5],["c",1118,3],["l",1],["c",575,3],["l",29],["c",1162,41],["c",1162,8],["l",2]]}},{"format":1,"codec":"golden-sun-static-sprite-mode3","pixels":4096,"stream_bytes":248,"encoded_bytes":187,"wrapper":{"split":112,"operations":[["c",1311,4],["l",1],["c",748,3],["l",3],["c",432,3],["l",3],["c",1133,4],["l",3],["c",600,3],["l",4],["c",1215,3],["l",1],["c",1129,3],["c",129,3],["l",1],["c",763,3],["c",585,3],["l",11],["c",566,3],["l",9],["c",77,3],["l",2],["c",99,5],["l",3],["c",186,3],["l",4],["c",1131,3],["l",2],["c",85,4],["l",2],["c",786,4],["l",1],["c",432,3],["l",17],["c",266,3],["l",3],["c",780,3],["l",1],["c",1349,12],["l",12],["c",1107,3],["l",2],["c",1154,3],["l",3],["c",147,3],["l",18],["c",76,3],["l",2],["c",1349,41],["c",1349,7],["l",2]]}},{"format":1,"codec":"golden-sun-static-sprite-mode3","pixels":4096,"stream_bytes":327,"encoded_bytes":262,"wrapper":{"split":164,"operations":[["c",1536,17],["c",1148,3],["l",1],["c",453,4],["l",1],["c",1484,3],["c",1371,5],["l",6],["c",1403,4],["c",1347,3],["c",1200,3],["c",136,3],["l",21],["c",366,3],["l",5],["c",1375,3],["l",10],["c",1387,3],["l",11],["c",1485,4],["l",13],["c",1376,3],["l",4],["c",1008,3],["l",10],["c",787,3],["l",1],["c",780,3],["c",136,3],["l",9],["c",1480,3],["l",5],["c",1337,4],["l",1],["c",1456,3],["l",12],["c",1355,3],["l",3],["c",1375,3],["l",2],["c",1464,3],["l",2],["c",772,3],["l",3],["c",1536,5],["l",1],["c",128,3],["l",2],["c",453,3],["l",7],["c",949,3],["l",10],["c",354,3],["c",949,3],["l",11],["c",272,4],["l",2],["c",273,5],["l",4],["c",355,3],["l",3],["c",1536,38],["l",2]]}},{"format":1,"codec":"golden-sun-static-sprite-mode3","pixels":4096,"stream_bytes":279,"encoded_bytes":204,"wrapper":{"split":110,"operations":[["c",1798,14],["c",1271,3],["c",1639,3],["c",880,3],["c",1303,3],["l",4],["c",1622,4],["l",3],["c",1304,3],["c",1636,3],["l",4],["c",1754,3],["l",2],["c",1076,3],["l",6],["c",578,3],["l",4],["c",1226,3],["l",1],["c",758,4],["l",6],["c",1233,3],["c",1651,3],["l",13],["c",1408,3],["l",13],["c",1212,4],["l",8],["c",1408,3],["c",1203,3],["l",1],["c",1039,3],["l",1],["c",1622,4],["l",5],["c",1744,3],["l",3],["c",943,3],["l",2],["c",1664,3],["l",1],["c",1733,3],["l",5],["c",1639,3],["l",2],["c",1702,3],["l",4],["c",1245,3],["l",3],["c",580,4],["c",635,3],["l",1],["c",1034,3],["l",1],["c",578,3],["l",1],["c",369,3],["l",7],["c",388,3],["l",5],["c",1798,41],["c",1798,12],["l",2]]}},{"format":1,"codec":"golden-sun-static-sprite-mode3","pixels":4096,"stream_bytes":324,"encoded_bytes":220,"wrapper":{"split":102,"operations":[["c",2002,17],["l",2],["c",1431,3],["c",1224,3],["l",2],["c",1843,3],["l",1],["c",1514,4],["c",1849,3],["l",1],["c",202,3],["c",1814,4],["l",3],["c",1760,3],["l",4],["c",454,5],["l",2],["c",447,10],["c",832,3],["l",5],["c",1760,3],["l",4],["c",428,3],["l",6],["c",422,3],["l",3],["c",415,4],["l",2],["c",1424,3],["l",7],["c",403,3],["l",5],["c",398,4],["c",1474,3],["c",394,8],["l",2],["c",1253,3],["l",1],["c",1246,4],["c",1779,3],["l",1],["c",1640,3],["l",2],["c",751,3],["l",2],["c",374,5],["l",1],["c",367,3],["l",1],["c",1922,3],["c",368,7],["l",2],["c",359,3],["l",1],["c",786,4],["c",602,3],["l",2],["c",1430,3],["c",793,3],["c",1214,3],["l",2],["c",2002,5],["l",1],["c",594,3],["l",2],["c",598,3],["l",3],["c",340,4],["c",1415,3],["l",3],["c",333,4],["l",2],["c",340,3],["l",1],["c",1415,3],["l",11],["c",738,4],["l",3],["c",166,3],["l",5],["c",821,3],["l",3],["c",2002,38],["l",2]]}},{"format":1,"codec":"golden-sun-static-sprite-mode3","pixels":4096,"stream_bytes":282,"encoded_bytes":189,"wrapper":{"split":80,"operations":[["c",2222,14],["l",1],["c",177,3],["c",176,3],["l",8],["c",2046,4],["l",2],["c",1702,3],["c",2060,3],["l",4],["c",2178,3],["l",2],["c",1500,3],["l",1],["c",410,4],["l",2],["c",1002,3],["l",1],["c",1721,3],["c",1650,3],["l",1],["c",2041,3],["l",5],["c",532,3],["l",2],["c",1641,3],["l",7],["c",387,6],["c",2057,3],["c",381,4],["l",8],["c",2180,3],["c",1999,3],["l",1],["c",1830,3],["c",364,4],["c",1832,3],["l",8],["c",2088,3],["l",6],["c",2138,3],["l",3],["c",1367,3],["c",327,3],["c",2088,3],["l",2],["c",1473,3],["c",340,3],["c",797,3],["c",2056,4],["l",1],["c",2126,3],["c",347,3],["c",1434,3],["l",1],["c",1651,4],["c",153,3],["c",323,3],["c",2158,4],["l",1],["c",2150,3],["l",1],["c",813,3],["l",2],["c",328,4],["l",3],["c",2061,3],["l",3],["c",2222,41],["c",2222,12],["l",2]]}},{"format":1,"codec":"golden-sun-static-sprite-mode3","pixels":4096,"stream_bytes":335,"encoded_bytes":256,"wrapper":{"split":161,"operations":[["c",2401,33],["c",1818,3],["l",1],["c",2359,3],["l",1],["c",365,3],["l",8],["c",1883,3],["l",5],["c",791,3],["l",1],["c",2236,4],["l",8],["c",2339,3],["l",9],["c",535,3],["l",10],["c",1191,3],["l",8],["c",2367,3],["l",1],["c",607,3],["l",8],["c",2291,4],["l",1],["c",2020,3],["l",6],["c",366,4],["l",4],["c",2358,3],["l",1],["c",183,4],["l",1],["c",2091,3],["l",6],["c",2235,4],["l",1],["c",2264,3],["c",2030,5],["l",7],["c",1167,3],["l",4],["c",849,3],["l",3],["c",1845,3],["l",3],["c",2037,3],["c",2371,3],["l",10],["c",2091,4],["l",1],["c",1653,3],["l",17],["c",2087,3],["l",7],["c",1825,3],["l",14],["c",1854,3],["l",11],["c",2411,41],["c",2411,4],["l",2]]}},{"format":1,"codec":"golden-sun-static-sprite-mode3","pixels":4096,"stream_bytes":251,"encoded_bytes":158,"wrapper":{"split":92,"operations":[["c",2667,30],["l",1],["c",622,3],["l",1],["c",1255,3],["l",1],["c",2180,3],["c",780,3],["l",1],["c",2269,4],["c",2492,3],["l",16],["c",2316,4],["l",4],["c",1259,3],["l",4],["c",2607,3],["l",7],["c",1033,3],["l",14],["c",1040,3],["c",1062,3],["c",2625,3],["c",2508,3],["l",4],["c",143,3],["l",12],["c",2498,3],["c",2305,3],["l",3],["c",1053,3],["c",844,3],["l",7],["c",1100,3],["l",13],["c",2667,41],["c",2667,28],["l",2]]}},{"format":1,"codec":"golden-sun-static-sprite-mode3","pixels":4096,"stream_bytes":224,"encoded_bytes":136,"wrapper":{"split":73,"operations":[["c",2825,41],["l",2],["c",2224,3],["l",4],["c",1742,3],["l",6],["c",1425,3],["l",6],["c",2494,3],["l",4],["c",2076,3],["l",1],["c",592,3],["l",1],["c",2337,5],["l",7],["c",2674,3],["l",2],["c",1197,3],["l",11],["c",292,3],["l",3],["c",1155,3],["l",2],["c",2825,26],["l",2],["c",1636,3],["l",1],["c",2543,4],["l",1],["c",2057,3],["l",2],["c",2729,3],["l",4],["c",1399,4],["l",2],["c",1623,3],["l",4],["c",1566,5],["c",1190,3],["l",3],["c",931,3],["l",1],["c",2825,20],["l",2]]}},{"format":1,"codec":"golden-sun-static-sprite-mode3","pixels":4096,"stream_bytes":321,"encoded_bytes":257,"wrapper":{"split":160,"operations":[["c",2961,41],["c",2961,4],["l",2],["c",1591,3],["l",5],["c",2710,4],["l",5],["c",2917,3],["l",5],["c",2785,5],["l",2],["c",2050,3],["l",17],["c",1745,3],["l",1],["c",920,3],["l",1],["c",2787,3],["l",14],["c",934,3],["l",8],["c",1130,3],["l",1],["c",2563,3],["l",4],["c",459,3],["c",1074,3],["l",1],["c",2044,3],["l",7],["c",1593,3],["l",5],["c",2466,3],["c",877,3],["l",5],["c",2358,3],["c",2046,3],["l",33],["c",2902,3],["l",3],["c",2825,3],["l",1],["c",1791,3],["l",2],["c",1791,3],["l",3],["c",2744,3],["l",1],["c",2074,3],["c",1302,3],["l",4],["c",2389,5],["c",437,3],["l",16],["c",496,3],["l",1],["c",1702,3],["l",4],["c",1513,4],["l",5],["c",2961,19],["l",2]]}},{"format":1,"codec":"golden-sun-static-sprite-mode3","pixels":4096,"stream_bytes":245,"encoded_bytes":147,"wrapper":{"split":87,"operations":[["c",3218,41],["c",3218,9],["l",7],["c",1613,3],["l",2],["c",993,4],["l",3],["c",1382,3],["l",1],["c",3170,4],["l",6],["c",1610,3],["l",18],["c",2846,3],["l",6],["c",1380,3],["l",1],["c",1385,3],["l",4],["c",2898,3],["l",5],["c",3071,3],["l",7],["c",2040,3],["l",4],["c",1863,3],["c",2448,3],["c",355,3],["l",3],["c",1596,3],["c",232,3],["l",1],["c",1177,3],["l",15],["c",3218,41],["c",3218,16],["l",2]]}},{"format":1,"codec":"golden-sun-static-sprite-mode3","pixels":4096,"stream_bytes":228,"encoded_bytes":137,"wrapper":{"split":83,"operations":[["c",3365,41],["l",5],["c",3113,3],["l",4],["c",1566,3],["l",13],["c",3281,3],["l",2],["c",1284,3],["l",4],["c",2317,3],["l",9],["c",3299,3],["l",9],["c",3034,3],["l",4],["c",1140,4],["l",1],["c",2965,3],["l",1],["c",3232,3],["c",2289,3],["c",3034,3],["l",4],["c",1965,3],["l",14],["c",1529,3],["l",7],["c",1729,3],["l",2],["c",3365,41],["c",3365,19],["l",2]]}},{"format":1,"codec":"golden-sun-static-sprite-mode3","pixels":4096,"stream_bytes":188,"encoded_bytes":81,"wrapper":{"split":45,"operations":[["c",3502,41],["c",3502,34],["c",3502,42],["l",4],["c",466,4],["l",1],["c",1033,3],["l",8],["c",283,3],["l",16],["c",3460,3],["l",3],["c",794,3],["l",3],["c",797,3],["l",2],["c",2745,3],["l",2],["c",794,3],["l",2],["c",3502,3],["l",2]]}},{"format":1,"codec":"golden-sun-static-sprite-mode3","pixels":4096,"stream_bytes":129,"encoded_bytes":17,"wrapper":{"split":3,"operations":[["c",3583,41],["c",3583,41],["c",3583,41],["c",3583,5],["l",1]]}}],"directory":[0,1,2,3,4,5,6,7,8,9,10,11,12,13,14,15,16,17,18,19]}
