{"format":1,"codec":"golden-sun-static-sprite-bank","width":32,"height":32,"alignment_zeros":3,"frames":[{"format":1,"codec":"golden-sun-static-sprite-mode3","pixels":1024,"stream_bytes":332,"encoded_bytes":334,"wrapper":{"split":0}},{"format":1,"codec":"golden-sun-static-sprite-mode3","pixels":1024,"stream_bytes":337,"encoded_bytes":339,"wrapper":{"split":0}},{"format":1,"codec":"golden-sun-static-sprite-mode3","pixels":1024,"stream_bytes":330,"encoded_bytes":332,"wrapper":{"split":0}},{"format":1,"codec":"golden-sun-static-sprite-mode3","pixels":1024,"stream_bytes":332,"encoded_bytes":41,"wrapper":{"split":21,"operations":[["c",1005,87],["l",1],["c",917,8],["c",755,3],["l",4],["c",902,6],["l",8],["c",888,6],["l",6],["c",876,203]]}},{"format":1,"codec":"golden-sun-static-sprite-mode3","pixels":1024,"stream_bytes":337,"encoded_bytes":20,"wrapper":{"split":6,"operations":[["c",712,86],["l",1],["c",625,11],["l",1],["c",613,12],["l",2],["c",599,224]]}},{"format":1,"codec":"golden-sun-static-sprite-mode3","pixels":1024,"stream_bytes":330,"encoded_bytes":11,"wrapper":{"split":2,"operations":[["c",393,273],["c",120,57]]}},{"format":1,"codec":"golden-sun-static-sprite-mode3","pixels":1024,"stream_bytes":329,"encoded_bytes":173,"wrapper":{"split":109,"operations":[["c",743,6],["l",3],["c",767,3],["l",3],["c",263,6],["l",2],["c",1062,4],["l",6],["c",1052,4],["l",31],["c",231,4],["l",3],["c",307,3],["l",2],["c",214,3],["l",2],["c",1030,3],["l",3],["c",1032,3],["c",722,5],["c",427,3],["l",5],["c",949,3],["l",8],["c",957,3],["l",9],["c",945,4],["l",5],["c",936,3],["c",918,5],["l",17],["c",912,4],["l",1],["c",991,3],["l",5],["c",1035,3],["l",1],["c",895,8],["l",1],["c",884,139]]}},{"format":1,"codec":"golden-sun-static-sprite-mode3","pixels":1024,"stream_bytes":332,"encoded_bytes":194,"wrapper":{"split":108,"operations":[["c",577,6],["c",909,4],["l",8],["c",895,5],["l",3],["c",942,3],["l",1],["c",895,4],["c",1190,3],["l",3],["c",563,3],["l",1],["c",1208,4],["l",7],["c",845,3],["l",2],["c",365,3],["l",10],["c",856,4],["c",838,3],["l",3],["c",718,3],["l",1],["c",1073,4],["l",9],["c",777,6],["l",2],["c",523,3],["l",2],["c",463,6],["l",6],["c",777,6],["l",2],["c",1158,3],["l",2],["c",1187,3],["l",1],["c",812,3],["l",8],["c",394,4],["l",9],["c",1117,3],["c",388,3],["c",743,6],["c",884,3],["l",6],["c",727,4],["l",5],["c",717,8],["l",5],["c",702,8],["l",5],["c",689,8],["l",4],["c",677,19],["l",1],["c",657,78]]}},{"format":1,"codec":"golden-sun-static-sprite-mode3","pixels":1024,"stream_bytes":328,"encoded_bytes":192,"wrapper":{"split":92,"operations":[["c",1444,5],["l",1],["c",100,3],["l",1],["c",762,4],["c",1398,3],["c",194,3],["l",4],["c",653,7],["l",1],["c",727,3],["l",1],["c",1076,5],["c",594,3],["l",4],["c",1267,3],["l",3],["c",581,3],["l",3],["c",1356,3],["c",327,3],["l",1],["c",568,3],["l",8],["c",602,3],["l",3],["c",1386,3],["c",308,3],["l",2],["c",1075,4],["c",555,4],["l",2],["c",726,4],["l",1],["c",598,6],["l",3],["c",971,6],["l",1],["c",969,5],["l",2],["c",759,3],["l",1],["c",598,5],["l",4],["c",559,3],["l",3],["c",598,3],["c",607,8],["l",2],["c",597,6],["c",605,4],["c",557,3],["l",2],["c",582,3],["l",7],["c",585,5],["l",4],["c",562,3],["l",1],["c",1074,3],["l",2],["c",1054,3],["l",3],["c",503,3],["l",1],["c",546,3],["l",4],["c",537,3],["l",15],["c",529,88]]}},{"format":1,"codec":"golden-sun-static-sprite-mode3","pixels":1024,"stream_bytes":329,"encoded_bytes":172,"wrapper":{"split":105,"operations":[["c",1636,4],["l",6],["c",1628,7],["l",1],["c",135,3],["l",2],["c",539,3],["l",1],["c",781,3],["l",7],["c",1588,4],["l",4],["c",520,3],["l",1],["c",1593,3],["l",3],["c",1274,3],["l",4],["c",806,3],["l",3],["c",1319,3],["l",1],["c",747,4],["l",5],["c",902,3],["l",1],["c",1324,4],["c",1423,3],["l",16],["c",619,3],["l",8],["c",331,3],["l",6],["c",851,6],["l",9],["c",1243,4],["l",5],["c",1483,3],["l",4],["c",1107,4],["l",15],["c",1454,8],["c",1202,4],["l",1],["c",1442,138]]}},{"format":1,"codec":"golden-sun-static-sprite-mode3","pixels":1024,"stream_bytes":338,"encoded_bytes":208,"wrapper":{"split":98,"operations":[["c",1474,6],["c",1801,3],["l",5],["c",1800,4],["l",2],["c",1373,3],["l",2],["c",1113,6],["c",1447,4],["c",1103,5],["c",962,4],["l",4],["c",1430,4],["l",1],["c",1396,3],["l",4],["c",1209,3],["l",1],["c",692,3],["l",10],["c",982,3],["l",2],["c",1277,3],["l",3],["c",927,3],["l",1],["c",1413,4],["l",8],["c",1020,6],["l",1],["c",1489,3],["l",2],["c",1019,5],["l",2],["c",1331,3],["l",1],["c",1335,6],["c",1744,3],["l",5],["c",1101,6],["l",2],["c",492,3],["l",1],["c",1442,4],["l",1],["c",971,3],["l",6],["c",982,3],["l",1],["c",946,3],["l",3],["c",1299,4],["l",5],["c",1290,3],["l",1],["c",1285,5],["l",9],["c",1271,6],["l",1],["c",1440,4],["l",1],["c",1259,7],["l",2],["c",1213,3],["l",1],["c",1246,7],["l",2],["c",1223,3],["c",1234,18],["l",1],["c",1215,33],["l",1],["c",1181,10],["l",2],["c",1169,10],["l",1],["c",1158,6],["c",1510,3],["l",1],["c",1148,11]]}},{"format":1,"codec":"golden-sun-static-sprite-mode3","pixels":1024,"stream_bytes":337,"encoded_bytes":183,"wrapper":{"split":80,"operations":[["c",1682,6],["c",673,3],["c",1936,3],["l",1],["c",1330,3],["c",1045,3],["l",3],["c",1322,8],["l",4],["c",1321,6],["l",1],["c",1186,3],["l",1],["c",1967,3],["c",1127,4],["l",5],["c",1192,3],["c",1990,3],["l",1],["c",1264,4],["l",8],["c",1266,7],["l",6],["c",1647,4],["c",1249,3],["c",1956,3],["l",4],["c",1649,5],["l",2],["c",1973,4],["l",1],["c",1162,3],["l",1],["c",1227,9],["l",3],["c",1200,9],["c",1565,3],["l",1],["c",1226,8],["c",1318,5],["l",1],["c",1179,3],["c",1186,3],["l",1],["c",1170,3],["l",4],["c",1593,4],["l",5],["c",1290,3],["l",3],["c",1309,3],["c",1157,6],["l",3],["c",695,3],["l",1],["c",1516,3],["l",1],["c",1157,4],["l",7],["c",928,3],["c",1330,3],["c",550,3],["c",1664,3],["l",3],["c",1373,3],["l",4],["c",491,6],["l",3],["c",1101,88]]}},{"format":1,"codec":"golden-sun-static-sprite-mode3","pixels":1024,"stream_bytes":332,"encoded_bytes":181,"wrapper":{"split":113,"operations":[["c",2199,7],["c",2191,5],["l",1],["c",2186,4],["l",4],["c",723,3],["l",5],["c",2170,4],["l",9],["c",2156,5],["l",2],["c",1494,3],["l",5],["c",2140,3],["l",1],["c",1375,3],["l",1],["c",1479,3],["l",3],["c",2139,3],["c",1600,3],["l",3],["c",1118,3],["l",1],["c",1762,4],["l",30],["c",1058,4],["c",1760,3],["l",8],["c",2068,3],["l",3],["c",492,3],["l",13],["c",1719,4],["l",6],["c",1802,3],["l",5],["c",471,3],["l",7],["c",2017,7],["l",3],["c",2006,129],["l",1],["c",1876,9]]}},{"format":1,"codec":"golden-sun-static-sprite-mode3","pixels":1024,"stream_bytes":336,"encoded_bytes":194,"wrapper":{"split":97,"operations":[["c",2380,5],["l",2],["c",2038,3],["c",2372,3],["l",6],["c",2026,6],["l",5],["c",2015,5],["l",3],["c",732,3],["c",2334,3],["l",3],["c",1970,3],["l",5],["c",2311,3],["l",5],["c",1658,3],["l",3],["c",1658,3],["c",1974,3],["l",1],["c",1495,3],["l",9],["c",1620,5],["l",2],["c",302,3],["l",4],["c",1931,3],["l",8],["c",175,3],["c",1374,3],["c",2287,3],["l",3],["c",1497,3],["l",2],["c",1247,3],["l",2],["c",1910,7],["l",4],["c",1214,3],["l",2],["c",2338,3],["c",870,3],["l",4],["c",1884,5],["c",1983,3],["c",666,3],["l",1],["c",1872,6],["l",2],["c",1849,3],["l",4],["c",1857,5],["l",2],["c",1654,3],["l",3],["c",1844,6],["c",1579,3],["l",4],["c",1831,8],["l",4],["c",1819,11],["l",1],["c",1807,19],["l",1],["c",1787,78]]}},{"format":1,"codec":"golden-sun-static-sprite-mode3","pixels":1024,"stream_bytes":326,"encoded_bytes":194,"wrapper":{"split":105,"operations":[["c",2574,5],["l",5],["c",1892,5],["l",10],["c",1879,6],["l",2],["c",2513,3],["l",1],["c",2218,4],["l",1],["c",2136,3],["c",2212,3],["l",1],["c",2397,4],["l",11],["c",2151,4],["l",1],["c",689,3],["l",3],["c",493,3],["l",2],["c",497,3],["c",1834,3],["l",4],["c",2208,3],["l",10],["c",2208,6],["c",1795,3],["l",3],["c",1788,3],["c",1770,9],["c",1462,3],["c",1771,10],["l",2],["c",1784,8],["c",2216,3],["l",5],["c",1798,4],["c",1796,3],["l",2],["c",1748,3],["l",1],["c",354,4],["l",14],["c",2057,4],["l",2],["c",2140,5],["l",3],["c",1714,3],["l",5],["c",1724,4],["l",9],["c",1673,4],["c",1050,4],["l",5],["c",1660,6],["l",1],["c",1653,82]]}},{"format":1,"codec":"golden-sun-static-sprite-mode3","pixels":1024,"stream_bytes":318,"encoded_bytes":320,"wrapper":{"split":0}},{"format":1,"codec":"golden-sun-static-sprite-mode3","pixels":1024,"stream_bytes":344,"encoded_bytes":290,"wrapper":{"split":156,"operations":[["c",320,7],["l",1],["c",3080,4],["l",2],["c",2666,3],["c",1978,3],["l",5],["c",2393,6],["l",2],["c",2726,3],["l",2],["c",3046,4],["c",3020,3],["l",3],["c",2197,3],["l",1],["c",2665,4],["l",9],["c",2911,4],["l",10],["c",2911,4],["c",2237,3],["l",2],["c",1009,3],["l",1],["c",2301,6],["l",2],["c",2361,3],["l",5],["c",2733,4],["l",10],["c",2300,4],["l",4],["c",1922,3],["l",1],["c",2381,6],["l",2],["c",2621,3],["l",2],["c",2680,3],["l",1],["c",3045,4],["l",5],["c",2382,4],["l",9],["c",2576,4],["c",1049,3],["l",1],["c",1209,3],["l",2],["c",136,4],["c",2367,3],["c",1202,3],["l",7],["c",3024,3],["l",2],["c",2889,3],["l",2],["c",2188,3],["l",4],["c",2884,3],["l",2],["c",644,3],["c",2791,3],["l",1],["c",3070,3],["l",4],["c",2423,3],["l",2],["c",2501,3],["l",9],["c",2428,4],["l",4],["c",2949,3],["l",3],["c",2143,4],["c",2476,3],["l",9],["c",2164,3],["c",2477,4],["l",8],["c",2130,3],["l",1],["c",1949,4],["l",1],["c",1745,3],["l",2],["c",2491,3],["c",1949,4],["c",2438,4],["l",3],["c",1949,4],["l",5],["c",273,3],["l",3]]}},{"format":1,"codec":"golden-sun-static-sprite-mode3","pixels":1024,"stream_bytes":354,"encoded_bytes":270,"wrapper":{"split":134,"operations":[["c",2705,6],["c",2301,3],["l",3],["c",3371,4],["l",1],["c",2781,3],["l",3],["c",2587,7],["c",1507,3],["l",2],["c",3363,3],["c",2668,4],["c",2677,3],["c",1126,3],["c",2599,3],["c",2611,3],["c",2651,5],["l",2],["c",2261,3],["c",2626,4],["l",3],["c",2455,3],["l",2],["c",2924,3],["l",4],["c",3320,3],["l",3],["c",3201,4],["l",1],["c",760,4],["l",1],["c",753,3],["l",2],["c",2602,7],["l",1],["c",537,3],["l",2],["c",2589,9],["c",947,3],["l",3],["c",2587,7],["c",2940,3],["l",5],["c",2548,8],["l",5],["c",2536,5],["c",530,6],["l",3],["c",2599,3],["c",1301,3],["l",2],["c",2532,5],["l",7],["c",2517,5],["l",6],["c",987,4],["c",2861,4],["c",2516,3],["l",5],["c",2400,3],["c",1337,3],["c",552,5],["l",9],["c",3356,3],["l",7],["c",3116,3],["l",2],["c",2370,3],["l",10],["c",3115,3],["l",2],["c",322,4],["l",2],["c",2460,3],["l",3],["c",2430,4],["l",7],["c",2432,9],["l",4],["c",1542,3],["c",2416,6],["c",2332,3],["l",2],["c",2453,3],["l",4],["c",2434,3],["l",3],["c",2478,3],["l",5],["c",2465,3],["l",6]]}},{"format":1,"codec":"golden-sun-static-sprite-mode3","pixels":1024,"stream_bytes":342,"encoded_bytes":295,"wrapper":{"split":166,"operations":[["c",3648,6],["c",3434,3],["c",3639,6],["c",2821,3],["c",580,3],["l",1],["c",858,5],["l",3],["c",2386,3],["l",1],["c",846,5],["c",3609,4],["c",3606,5],["l",5],["c",1194,3],["c",2785,3],["l",1],["c",3588,4],["c",3633,3],["l",5],["c",2818,3],["l",4],["c",3603,5],["c",3602,4],["l",1],["c",790,4],["l",11],["c",3544,8],["l",4],["c",1202,3],["c",3528,3],["l",3],["c",754,3],["l",4],["c",2900,3],["l",3],["c",741,4],["l",17],["c",3488,4],["c",3235,3],["l",10],["c",508,3],["c",3157,3],["l",3],["c",3463,4],["l",11],["c",690,3],["l",18],["c",644,3],["l",11],["c",3376,3],["l",8],["c",636,3],["c",3376,3],["l",1],["c",644,3],["c",3422,3],["l",4],["c",3390,3],["c",3376,3],["l",9],["c",3376,3],["c",3389,3],["c",618,4],["l",3],["c",3376,3],["c",3389,3],["l",2],["c",3368,3],["l",3],["c",3061,3],["l",3],["c",3356,4],["c",2997,3],["l",2],["c",3431,3],["l",6],["c",1751,3],["l",3],["c",505,3],["l",4]]}},{"format":1,"codec":"golden-sun-static-sprite-mode3","pixels":1024,"stream_bytes":315,"encoded_bytes":265,"wrapper":{"split":147,"operations":[["c",3609,6],["c",3936,4],["l",3],["c",3257,3],["l",8],["c",3248,6],["l",6],["c",3103,4],["l",3],["c",2674,3],["c",3055,3],["l",1],["c",3766,4],["l",10],["c",3766,4],["l",5],["c",1865,3],["l",1],["c",3224,6],["l",7],["c",3588,5],["l",7],["c",3588,5],["l",7],["c",3587,4],["c",3814,3],["l",5],["c",3587,4],["l",1],["c",3802,3],["l",1],["c",3472,4],["c",1095,4],["l",7],["c",3901,3],["c",1902,3],["l",2],["c",3407,3],["l",4],["c",3195,4],["c",3544,3],["l",3],["c",991,3],["l",3],["c",3083,3],["l",2],["c",3420,3],["l",3],["c",3531,3],["l",5],["c",3289,3],["l",17],["c",1279,3],["l",3],["c",3729,3],["l",3],["c",2602,3],["c",467,3],["l",1],["c",160,3],["c",936,3],["l",1],["c",3025,3],["l",6],["c",3337,6],["l",1],["c",2924,3],["l",1],["c",3314,3],["l",5],["c",3803,3],["l",3],["c",3648,4],["l",1],["c",3921,3],["c",3287,3],["l",2],["c",3300,6],["c",2976,3],["l",4],["c",2045,6],["l",3]]}},{"format":1,"codec":"golden-sun-static-sprite-mode3","pixels":1024,"stream_bytes":346,"encoded_bytes":241,"wrapper":{"split":97,"operations":[["c",3534,5],["l",1],["c",3522,3],["l",3],["c",1430,3],["c",1823,3],["l",3],["c",3517,3],["c",3759,4],["l",5],["c",3417,7],["l",2],["c",3491,5],["l",1],["c",248,3],["c",2130,3],["c",3479,3],["l",2],["c",3812,4],["c",1370,3],["l",7],["c",184,3],["c",3471,5],["c",2329,3],["l",1],["c",1078,3],["c",3366,3],["c",3678,4],["l",2],["c",3436,6],["c",3362,5],["c",3757,3],["c",3435,5],["c",3417,8],["l",1],["c",3434,4],["c",3417,8],["l",2],["c",3417,7],["c",3851,3],["l",1],["c",2708,3],["l",3],["c",3513,6],["l",1],["c",2889,3],["c",1570,3],["c",3362,6],["l",1],["c",3355,9],["l",3],["c",2330,4],["l",4],["c",3335,4],["l",5],["c",3326,4],["l",1],["c",3796,3],["l",2],["c",2540,3],["c",824,3],["c",3600,3],["c",1430,3],["c",3860,3],["c",3110,3],["l",9],["c",3312,3],["l",8],["c",3595,3],["c",3642,3],["l",5],["c",3285,3],["l",5],["c",3267,4],["l",1],["c",3262,5],["l",4],["c",3267,4],["l",1],["c",3250,5],["l",3],["c",3243,11],["c",1176,3],["l",2],["c",3240,5],["c",3558,3],["l",1],["c",4018,3],["l",1],["c",3216,4],["c",1789,3],["l",2],["c",3626,4],["l",2],["c",123,3]]}},{"format":1,"codec":"golden-sun-static-sprite-mode3","pixels":1024,"stream_bytes":340,"encoded_bytes":342,"wrapper":{"split":0}},{"format":1,"codec":"golden-sun-static-sprite-mode3","pixels":1024,"stream_bytes":341,"encoded_bytes":343,"wrapper":{"split":0}},{"format":1,"codec":"golden-sun-static-sprite-mode3","pixels":1024,"stream_bytes":333,"encoded_bytes":292,"wrapper":{"split":171,"operations":[["c",2366,4],["l",2],["c",334,4],["c",2919,3],["l",3],["c",669,4],["c",1188,3],["l",2],["c",2930,3],["c",2285,7],["l",3],["c",256,3],["l",1],["c",635,4],["l",4],["c",2532,3],["l",1],["c",902,3],["c",1740,4],["l",4],["c",1727,3],["l",6],["c",2030,3],["l",5],["c",3999,3],["l",2],["c",1740,3],["l",5],["c",216,4],["c",635,4],["l",6],["c",2285,6],["l",7],["c",2285,7],["l",6],["c",2285,6],["l",1],["c",306,3],["c",256,4],["c",2306,3],["l",2],["c",608,3],["l",8],["c",1703,3],["l",4],["c",178,5],["l",6],["c",2317,3],["l",1],["c",2694,3],["l",2],["c",1703,3],["l",2],["c",2929,3],["c",1146,3],["l",3],["c",260,3],["l",1],["c",2556,3],["l",2],["c",2281,4],["l",9],["c",657,3],["l",9],["c",2359,3],["l",17],["c",1339,3],["l",7],["c",1933,3],["l",9],["c",2101,3],["l",8],["c",1122,3],["l",6],["c",27,3],["l",6],["c",3829,4],["c",27,3],["l",4],["c",3669,3],["l",1],["c",27,3],["l",4]]}},{"format":1,"codec":"golden-sun-static-sprite-mode3","pixels":1024,"stream_bytes":333,"encoded_bytes":279,"wrapper":{"split":165,"operations":[["c",2658,7],["l",2],["c",895,3],["l",2],["c",2644,3],["l",4],["c",2614,4],["l",1],["c",2631,3],["c",2626,3],["l",2],["c",3612,3],["l",2],["c",2618,5],["c",2637,3],["c",2610,6],["l",1],["c",1194,3],["l",1],["c",900,3],["l",1],["c",3768,3],["l",2],["c",2590,6],["l",7],["c",3941,3],["l",1],["c",2573,5],["c",878,4],["l",3],["c",2580,3],["l",2],["c",880,3],["l",4],["c",2550,8],["l",9],["c",1742,4],["l",6],["c",3941,3],["l",6],["c",3716,3],["c",2002,4],["l",1],["c",2620,6],["c",1721,3],["l",2],["c",3127,3],["l",3],["c",1713,3],["l",9],["c",1705,3],["l",37],["c",744,3],["l",9],["c",685,4],["l",2],["c",2278,3],["l",4],["c",730,5],["l",1],["c",2414,3],["l",2],["c",746,5],["c",683,3],["l",6],["c",702,7],["l",4],["c",2393,4],["c",715,6],["l",3],["c",382,4],["l",12],["c",319,3],["l",1],["c",3527,4],["l",8],["c",2283,3],["l",3]]}},{"format":1,"codec":"golden-sun-static-sprite-mode3","pixels":1024,"stream_bytes":339,"encoded_bytes":293,"wrapper":{"split":166,"operations":[["c",2937,7],["l",2],["c",1241,3],["l",3],["c",1240,4],["l",2],["c",1903,3],["l",2],["c",2856,5],["l",6],["c",881,4],["c",495,3],["c",2605,3],["c",3671,4],["c",3081,3],["l",2],["c",2600,4],["l",2],["c",856,6],["l",2],["c",848,4],["c",857,3],["c",738,3],["l",1],["c",1206,4],["l",2],["c",2308,3],["l",14],["c",814,6],["c",2572,3],["c",1708,3],["l",3],["c",1240,3],["l",2],["c",794,4],["l",1],["c",3500,3],["l",11],["c",1473,3],["l",1],["c",757,4],["c",2661,3],["l",1],["c",793,3],["l",3],["c",3411,3],["c",684,3],["c",4039,3],["l",11],["c",3844,3],["c",3637,3],["c",193,3],["c",2759,3],["l",13],["c",1962,3],["l",9],["c",1037,3],["l",25],["c",2784,3],["l",7],["c",1002,3],["l",14],["c",1183,3],["l",6],["c",158,3],["c",655,3],["c",1632,3],["l",4],["c",598,4],["c",949,4],["l",2],["c",1439,3],["c",614,3],["l",1],["c",596,5],["l",5],["c",598,6],["l",5],["c",949,4],["l",2]]}},{"format":1,"codec":"golden-sun-static-sprite-mode3","pixels":1024,"stream_bytes":326,"encoded_bytes":280,"wrapper":{"split":147,"operations":[["c",3230,5],["l",3],["c",533,3],["l",2],["c",1537,3],["l",7],["c",3149,7],["l",2],["c",805,4],["l",2],["c",1496,4],["l",2],["c",3746,3],["c",1170,3],["c",3921,3],["c",260,3],["l",5],["c",1117,3],["l",6],["c",1777,3],["c",3759,3],["l",2],["c",842,4],["l",8],["c",845,3],["c",2567,3],["l",7],["c",1173,5],["c",1766,3],["c",904,3],["c",1107,6],["c",1171,3],["c",1078,3],["l",1],["c",815,4],["l",1],["c",1080,4],["c",1078,3],["l",2],["c",3149,5],["l",2],["c",2010,3],["l",1],["c",3057,3],["c",1472,3],["c",2038,3],["l",4],["c",1174,3],["l",7],["c",1011,3],["c",1016,4],["l",2],["c",3149,4],["l",8],["c",845,3],["c",3920,3],["l",2],["c",1105,4],["l",1],["c",3404,3],["l",6],["c",1228,3],["l",18],["c",2764,3],["l",2],["c",2978,4],["l",11],["c",3766,3],["c",158,3],["l",2],["c",2941,3],["l",2],["c",2205,3],["l",4],["c",769,3],["l",11],["c",769,3],["l",2],["c",730,3],["c",838,3],["c",891,3],["l",3],["c",2613,3],["l",1],["c",838,3],["c",891,3],["l",6]]}},{"format":1,"codec":"golden-sun-static-sprite-mode3","pixels":1024,"stream_bytes":341,"encoded_bytes":273,"wrapper":{"split":148,"operations":[["c",3510,5],["l",3],["c",1817,5],["l",8],["c",1511,3],["l",3],["c",2629,4],["l",3],["c",3476,5],["l",5],["c",3429,4],["l",1],["c",3461,4],["l",1],["c",2046,3],["l",2],["c",3681,3],["c",233,3],["c",2046,3],["c",2618,3],["l",8],["c",3617,3],["c",813,3],["c",3450,3],["l",3],["c",1729,4],["l",5],["c",2603,5],["l",12],["c",3832,3],["l",14],["c",1332,3],["l",2],["c",3371,4],["l",1],["c",2583,5],["l",4],["c",2574,3],["l",5],["c",1672,4],["l",2],["c",2567,3],["l",1],["c",2563,3],["l",2],["c",1428,4],["c",1448,3],["c",3973,3],["l",1],["c",1645,3],["l",5],["c",2548,5],["c",3320,3],["c",2543,3],["l",7],["c",2533,5],["l",6],["c",2525,9],["l",2],["c",1596,3],["l",5],["c",1573,4],["l",2],["c",1582,5],["l",3],["c",1559,3],["l",1],["c",3266,3],["c",1582,5],["l",3],["c",2498,6],["c",1567,6],["c",3248,4],["l",3],["c",1567,6],["l",2],["c",3246,3],["l",1],["c",1211,3],["l",9],["c",1172,7],["l",1],["c",1980,4],["l",1],["c",1167,4],["l",9]]}},{"format":1,"codec":"golden-sun-static-sprite-mode3","pixels":1024,"stream_bytes":311,"encoded_bytes":258,"wrapper":{"split":135,"operations":[["c",3782,7],["c",2090,3],["l",2],["c",2086,3],["c",2605,8],["l",1],["c",3702,5],["l",2],["c",2595,4],["c",1347,3],["l",1],["c",2591,3],["l",7],["c",1700,4],["l",4],["c",2583,3],["l",2],["c",1687,3],["l",4],["c",1680,3],["l",2],["c",3722,4],["c",2319,3],["l",4],["c",1676,3],["l",1],["c",1658,4],["l",3],["c",1384,3],["l",3],["c",1620,4],["l",1],["c",1379,3],["l",3],["c",1658,4],["l",3],["c",2550,5],["c",3702,4],["l",1],["c",1300,3],["l",5],["c",3703,4],["c",688,3],["c",2540,3],["l",3],["c",1671,4],["l",8],["c",1714,4],["l",5],["c",2530,3],["c",3599,3],["c",1480,3],["l",8],["c",2522,3],["l",10],["c",820,3],["l",4],["c",2508,4],["l",2],["c",2502,3],["l",15],["c",1475,3],["l",8],["c",1787,3],["l",2],["c",2489,5],["l",1],["c",442,3],["l",1],["c",2011,3],["l",1],["c",1833,3],["l",1],["c",442,3],["l",1],["c",2479,3],["l",5],["c",3531,3],["l",3],["c",1443,3],["l",3],["c",1445,6],["c",2094,3],["l",3],["c",1443,4],["c",2467,4]]}},{"format":1,"codec":"golden-sun-static-sprite-mode3","pixels":1024,"stream_bytes":349,"encoded_bytes":285,"wrapper":{"split":138,"operations":[["c",4041,4],["l",3],["c",2271,3],["c",808,3],["l",4],["c",1092,3],["l",2],["c",3960,6],["l",2],["c",1635,3],["l",1],["c",3960,7],["l",3],["c",764,3],["c",762,3],["l",8],["c",1856,4],["l",2],["c",3414,3],["c",2584,3],["l",10],["c",788,3],["l",1],["c",1636,3],["l",7],["c",3378,3],["l",2],["c",1641,4],["l",1],["c",1982,3],["l",2],["c",1611,3],["l",5],["c",3960,7],["c",1656,3],["c",3992,3],["l",2],["c",3960,7],["l",1],["c",1918,6],["l",1],["c",3960,5],["c",768,3],["l",2],["c",3960,7],["l",1],["c",466,3],["l",2],["c",2294,3],["l",1],["c",2283,4],["l",2],["c",3882,3],["c",1599,3],["l",1],["c",1962,3],["c",506,3],["l",4],["c",2560,3],["c",1602,3],["c",2558,3],["l",2],["c",1634,3],["l",1],["c",1599,3],["l",1],["c",2309,4],["l",1],["c",3425,3],["l",1],["c",805,4],["c",4034,3],["l",10],["c",2544,3],["l",4],["c",3605,3],["l",6],["c",139,3],["l",1],["c",1750,3],["l",4],["c",4022,3],["l",2],["c",1254,3],["l",2],["c",3014,3],["l",6],["c",2060,4],["l",2],["c",1533,4],["c",1704,3],["l",2],["c",3592,3],["l",2],["c",1532,3],["c",1718,3],["l",6],["c",1776,4],["l",8],["c",2353,3],["l",1],["c",3347,3],["l",3],["c",3753,3],["l",1],["c",2724,3]]}},{"format":1,"codec":"golden-sun-static-sprite-mode3","pixels":1024,"stream_bytes":321,"encoded_bytes":276,"wrapper":{"split":156,"operations":[["c",2645,7],["l",2],["c",2636,5],["c",2281,5],["c",2626,3],["l",2],["c",2621,4],["l",3],["c",2614,7],["l",1],["c",2607,3],["l",5],["c",3138,3],["l",1],["c",1916,3],["l",4],["c",1084,3],["l",3],["c",3698,3],["l",5],["c",3069,3],["l",1],["c",2568,4],["l",1],["c",2563,3],["l",2],["c",1650,3],["l",2],["c",2552,4],["l",2],["c",2546,3],["c",502,3],["l",6],["c",3417,3],["l",1],["c",2529,5],["l",2],["c",765,4],["l",3],["c",2161,3],["l",1],["c",2510,5],["l",1],["c",2258,3],["l",12],["c",3870,3],["l",2],["c",2130,3],["l",11],["c",3383,3],["l",4],["c",2446,3],["l",4],["c",3365,4],["l",7],["c",2440,3],["l",3],["c",280,3],["l",11],["c",1852,3],["l",1],["c",2412,3],["l",5],["c",1028,3],["l",1],["c",2353,3],["l",1],["c",699,3],["l",3],["c",4082,3],["c",2369,4],["l",10],["c",2412,4],["l",7],["c",2369,5],["l",4],["c",2050,3],["l",7],["c",686,4],["l",1],["c",1988,4],["l",1],["c",165,5],["l",8],["c",2312,3],["l",3],["c",3009,3]]}},{"format":1,"codec":"golden-sun-static-sprite-mode3","pixels":1024,"stream_bytes":332,"encoded_bytes":274,"wrapper":{"split":136,"operations":[["c",2921,6],["l",5],["c",3567,3],["l",8],["c",2477,4],["l",1],["c",2552,5],["l",1],["c",2187,4],["c",2868,3],["l",1],["c",2538,7],["c",3138,3],["l",1],["c",2527,4],["l",5],["c",2867,3],["l",3],["c",2512,3],["c",3375,3],["c",2506,5],["c",3115,3],["l",2],["c",2869,3],["l",1],["c",2187,4],["l",9],["c",2492,4],["l",3],["c",3388,3],["l",2],["c",2480,3],["c",1064,3],["l",1],["c",2460,6],["l",3],["c",1064,3],["l",1],["c",3388,3],["l",3],["c",2187,3],["c",2439,5],["l",8],["c",504,5],["l",5],["c",3352,3],["c",2217,3],["l",10],["c",2222,3],["l",1],["c",2515,3],["c",2776,3],["l",3],["c",2176,3],["l",4],["c",2745,3],["l",3],["c",522,3],["l",9],["c",2294,3],["c",3634,3],["c",3327,3],["c",3889,3],["l",8],["c",2337,3],["c",3665,3],["c",2112,3],["l",4],["c",2281,4],["c",1508,3],["c",3128,3],["l",1],["c",1649,3],["l",3],["c",454,3],["c",2848,3],["l",1],["c",1530,3],["l",4],["c",2337,3],["l",1],["c",2614,4],["c",2617,3],["l",2],["c",2280,4],["c",3297,3],["l",6],["c",2336,4],["c",2260,4],["l",5],["c",2262,5],["l",6]]}},{"format":1,"codec":"golden-sun-static-sprite-mode3","pixels":1024,"stream_bytes":356,"encoded_bytes":285,"wrapper":{"split":136,"operations":[["c",3195,5],["l",5],["c",1913,3],["l",2],["c",3179,4],["c",3698,3],["l",3],["c",2728,5],["c",2831,4],["l",3],["c",2766,4],["c",3412,3],["l",1],["c",1632,3],["l",3],["c",3067,3],["c",2660,4],["c",1615,3],["c",2493,3],["l",3],["c",804,4],["l",5],["c",810,4],["l",3],["c",1033,4],["c",1615,3],["l",3],["c",2461,4],["c",3118,4],["c",3143,3],["c",2475,3],["l",1],["c",2831,5],["c",2831,4],["l",1],["c",3955,3],["l",1],["c",2831,5],["c",2831,4],["l",4],["c",2831,5],["c",2831,5],["l",1],["c",1043,3],["c",2446,3],["l",2],["c",2831,5],["c",1301,3],["l",1],["c",1575,3],["l",3],["c",2817,4],["l",6],["c",503,3],["l",1],["c",2660,4],["l",8],["c",2437,3],["l",2],["c",2435,3],["l",1],["c",219,3],["l",3],["c",2431,3],["l",1],["c",1340,4],["l",5],["c",3179,4],["l",17],["c",2176,3],["l",2],["c",449,3],["l",3],["c",726,3],["l",15],["c",2539,3],["l",6],["c",729,3],["l",4],["c",1537,4],["l",3],["c",2378,4],["l",1],["c",1537,4],["l",2],["c",2379,5],["l",2],["c",2883,5],["l",1],["c",2379,5],["c",2553,3],["c",2354,3],["l",1],["c",2484,3],["c",2377,3],["c",2351,4],["l",1],["c",2877,3],["c",728,3],["l",4],["c",143,3]]}},{"format":1,"codec":"golden-sun-static-sprite-mode3","pixels":1024,"stream_bytes":316,"encoded_bytes":318,"wrapper":{"split":0}},{"format":1,"codec":"golden-sun-static-sprite-mode3","pixels":1024,"stream_bytes":339,"encoded_bytes":295,"wrapper":{"split":186,"operations":[["c",318,8],["l",2],["c",1309,3],["l",1],["c",3788,3],["l",2],["c",3124,4],["l",11],["c",2803,3],["l",1],["c",3354,4],["l",1],["c",3781,3],["l",3],["c",1387,3],["c",1623,3],["l",10],["c",285,5],["c",3738,3],["l",2],["c",250,3],["l",3],["c",2796,3],["l",1],["c",1906,3],["l",17],["c",3181,3],["l",11],["c",2493,3],["c",3663,3],["l",11],["c",82,4],["c",507,3],["l",5],["c",1643,3],["l",1],["c",3991,3],["c",2495,3],["l",6],["c",3609,3],["c",1357,3],["c",3199,5],["l",1],["c",526,3],["l",5],["c",1932,3],["l",6],["c",81,3],["l",8],["c",1314,3],["l",2],["c",66,3],["l",1],["c",1906,3],["l",16],["c",3139,3],["l",20],["c",1864,3],["l",7],["c",116,3],["l",3],["c",3551,4],["l",7],["c",3551,4],["l",9],["c",3536,6],["l",9],["c",3506,3],["l",2],["c",26,24]]}},{"format":1,"codec":"golden-sun-static-sprite-mode3","pixels":1024,"stream_bytes":336,"encoded_bytes":272,"wrapper":{"split":165,"operations":[["c",613,8],["l",5],["c",3444,3],["l",3],["c",4053,4],["l",9],["c",4041,4],["l",3],["c",4044,4],["l",3],["c",1718,3],["l",2],["c",1973,3],["l",2],["c",3370,3],["l",1],["c",1973,3],["l",2],["c",2788,3],["l",4],["c",3291,3],["l",19],["c",2217,3],["l",7],["c",3993,3],["l",3],["c",1330,3],["l",10],["c",376,4],["l",2],["c",3441,4],["l",4],["c",3957,3],["l",2],["c",272,4],["l",1],["c",2419,3],["l",3],["c",1973,3],["l",5],["c",3836,3],["l",3],["c",272,3],["l",8],["c",3292,3],["l",7],["c",1444,3],["l",4],["c",3370,3],["l",11],["c",177,4],["c",2504,3],["l",2],["c",421,3],["l",10],["c",3375,3],["l",12],["c",272,4],["l",11],["c",144,3],["l",3],["c",3817,5],["c",138,7],["c",3846,4],["c",131,9],["c",3831,6],["c",122,9],["c",3801,3],["l",2],["c",321,24]]}},{"format":1,"codec":"golden-sun-static-sprite-mode3","pixels":1024,"stream_bytes":335,"encoded_bytes":251,"wrapper":{"split":124,"operations":[["c",885,8],["l",4],["c",1876,3],["c",1876,3],["l",2],["c",815,4],["l",3],["c",3998,3],["l",12],["c",1996,3],["l",1],["c",4058,3],["c",555,3],["l",1],["c",1955,4],["l",2],["c",849,5],["c",766,3],["l",3],["c",799,4],["l",3],["c",3642,3],["l",4],["c",2003,3],["l",1],["c",768,5],["c",3363,3],["l",11],["c",1582,3],["c",530,3],["l",13],["c",1062,3],["l",13],["c",1669,3],["l",1],["c",1666,3],["l",2],["c",1118,3],["l",5],["c",3092,3],["l",13],["c",3577,3],["c",648,3],["l",4],["c",679,4],["l",1],["c",3702,3],["c",2974,3],["c",628,3],["l",3],["c",648,3],["c",628,3],["c",544,4],["c",3706,3],["l",2],["c",609,4],["c",3714,3],["l",2],["c",2984,3],["l",1],["c",3691,3],["l",4],["c",629,4],["l",1],["c",3700,3],["c",684,3],["l",2],["c",1079,3],["l",2],["c",418,5],["c",3706,4],["l",3],["c",4073,4],["c",410,7],["c",4088,4],["c",403,9],["c",4088,5],["l",1],["c",394,9],["c",4073,3],["l",2],["c",593,24]]}}],"directory":[0,1,2,3,4,5,6,7,8,9,10,11,12,13,14,15,16,17,18,19,20,21,22,23,24,25,26,27,28,29,30,31,32,33,34,35,36]}
